{
  "autoRevoke": false,
  "packs": [
    {
      "packname": "blank",
      "url": "https://github.com/DBTDerpbox/LEB-Resources/blob/zip/zip/blank.zip?raw\u003dtrue",
      "hash": "",
      "required": true,
      "hasPrompt": true,
      "message": "Legacy Edition Battle requires a resource pack to function properly!",
      "packCompatibility": "BOTH"
    },
    {
      "packname": "vanilla",
      "url": "https://github.com/DBTDerpbox/LEB-Resources/blob/zip/zip/standard/R26.4/vanilla.zip?raw\u003dtrue",
      "hash": "",
      "required": true,
      "hasPrompt": true,
      "message": "Legacy Edition Battle requires a resource pack to function properly!",
      "packCompatibility": "VANILLA"
    },
    {
      "packname": "vanilla-optifine",
      "url": "https://github.com/DBTDerpbox/LEB-Resources/blob/zip/zip/optifine/R26.4/vanilla.zip?raw\u003dtrue",
      "hash": "",
      "required": true,
      "hasPrompt": true,
      "message": "Legacy Edition Battle requires a resource pack to function properly!",
      "packCompatibility": "OPTIFINE"
    },
    {
      "packname": "all-music-1",
      "url": "https://www.dropbox.com/s/ogycu8uzg696r8m/all-music-1.zip?dl\u003d1",
      "hash": "",
      "required": true,
      "hasPrompt": true,
      "message": "Legacy Edition Battle requires a resource pack to function properly!",
      "packCompatibility": "VANILLA"
    },
    {
      "packname": "all-music-1-optifine",
      "url": "https://www.dropbox.com/s/jza37nsig7h3idn/all-music-1.zip?dl\u003d1",
      "hash": "",
      "required": true,
      "hasPrompt": true,
      "message": "Legacy Edition Battle requires a resource pack to function properly!",
      "packCompatibility": "OPTIFINE"
    },
    {
      "packname": "plastic",
      "url": "https://github.com/DBTDerpbox/LEB-Resources/blob/zip/zip/standard/R26.4/plastic.zip?raw\u003dtrue",
      "hash": "",
      "required": true,
      "hasPrompt": true,
      "message": "Legacy Edition Battle requires a resource pack to function properly!",
      "packCompatibility": "VANILLA"
    },
    {
      "packname": "plastic-optifine",
      "url": "https://github.com/DBTDerpbox/LEB-Resources/blob/zip/zip/optifine/R26.4/plastic.zip?raw\u003dtrue",
      "hash": "",
      "required": true,
      "hasPrompt": true,
      "message": "Legacy Edition Battle requires a resource pack to function properly!",
      "packCompatibility": "OPTIFINE"
    },
    {
      "packname": "fantasy",
      "url": "https://github.com/DBTDerpbox/LEB-Resources/blob/zip/zip/standard/R26.4/fantasy.zip?raw\u003dtrue",
      "hash": "",
      "required": true,
      "hasPrompt": true,
      "message": "Legacy Edition Battle requires a resource pack to function properly!",
      "packCompatibility": "VANILLA"
    },
    {
      "packname": "fantasy-optifine",
      "url": "https://github.com/DBTDerpbox/LEB-Resources/blob/zip/zip/optifine/R26.4/fantasy.zip?raw\u003dtrue",
      "hash": "",
      "required": true,
      "hasPrompt": true,
      "message": "Legacy Edition Battle requires a resource pack to function properly!",
      "packCompatibility": "OPTIFINE"
    },
    {
      "packname": "city",
      "url": "https://github.com/DBTDerpbox/LEB-Resources/blob/zip/zip/standard/R26.4/city.zip?raw\u003dtrue",
      "hash": "",
      "required": true,
      "hasPrompt": true,
      "message": "Legacy Edition Battle requires a resource pack to function properly!",
      "packCompatibility": "VANILLA"
    },
    {
      "packname": "city-optifine",
      "url": "https://github.com/DBTDerpbox/LEB-Resources/blob/zip/zip/optifine/R26.4/city.zip?raw\u003dtrue",
      "hash": "",
      "required": true,
      "hasPrompt": true,
      "message": "Legacy Edition Battle requires a resource pack to function properly!",
      "packCompatibility": "OPTIFINE"
    },
    {
      "packname": "greek",
      "url": "https://github.com/DBTDerpbox/LEB-Resources/blob/zip/zip/standard/R26.4/greek-mythology.zip?raw\u003dtrue",
      "hash": "",
      "required": true,
      "hasPrompt": true,
      "message": "Legacy Edition Battle requires a resource pack to function properly!",
      "packCompatibility": "VANILLA"
    },
    {
      "packname": "greek-optifine",
      "url": "https://github.com/DBTDerpbox/LEB-Resources/blob/zip/zip/optifine/R26.4/greek-mythology.zip?raw\u003dtrue",
      "hash": "",
      "required": true,
      "hasPrompt": true,
      "message": "Legacy Edition Battle requires a resource pack to function properly!",
      "packCompatibility": "OPTIFINE"
    },
    {
      "packname": "steampunk",
      "url": "https://github.com/DBTDerpbox/LEB-Resources/blob/zip/zip/standard/R26.4/steampunk.zip?raw\u003dtrue",
      "hash": "",
      "required": true,
      "hasPrompt": true,
      "message": "Legacy Edition Battle requires a resource pack to function properly!",
      "packCompatibility": "VANILLA"
    },
    {
      "packname": "steampunk-optifine",
      "url": "https://github.com/DBTDerpbox/LEB-Resources/blob/zip/zip/optifine/R26.4/steampunk.zip?raw\u003dtrue",
      "hash": "",
      "required": true,
      "hasPrompt": true,
      "message": "Legacy Edition Battle requires a resource pack to function properly!",
      "packCompatibility": "OPTIFINE"
    },
    {
      "packname": "chinese",
      "url": "https://github.com/DBTDerpbox/LEB-Resources/blob/zip/zip/standard/R26.4/chinese-mythology.zip?raw\u003dtrue",
      "hash": "",
      "required": true,
      "hasPrompt": true,
      "message": "Legacy Edition Battle requires a resource pack to function properly!",
      "packCompatibility": "VANILLA"
    },
    {
      "packname": "chinese-optifine",
      "url": "https://github.com/DBTDerpbox/LEB-Resources/blob/zip/zip/optifine/R26.4/chinese-mythology.zip?raw\u003dtrue",
      "hash": "",
      "required": true,
      "hasPrompt": true,
      "message": "Legacy Edition Battle requires a resource pack to function properly!",
      "packCompatibility": "OPTIFINE"
    },
    {
      "packname": "halloween",
      "url": "https://github.com/DBTDerpbox/LEB-Resources/blob/zip/zip/standard/R26.4/halloween.zip?raw\u003dtrue",
      "hash": "",
      "required": true,
      "hasPrompt": true,
      "message": "Legacy Edition Battle requires a resource pack to function properly!",
      "packCompatibility": "VANILLA"
    },
    {
      "packname": "halloween-optifine",
      "url": "https://github.com/DBTDerpbox/LEB-Resources/blob/zip/zip/optifine/R26.4/halloween.zip?raw\u003dtrue",
      "hash": "",
      "required": true,
      "hasPrompt": true,
      "message": "Legacy Edition Battle requires a resource pack to function properly!",
      "packCompatibility": "OPTIFINE"
    },
    {
      "packname": "festive",
      "url": "https://github.com/DBTDerpbox/LEB-Resources/blob/zip/zip/standard/R26.4/festive.zip?raw\u003dtrue",
      "hash": "",
      "required": true,
      "hasPrompt": true,
      "message": "Legacy Edition Battle requires a resource pack to function properly!",
      "packCompatibility": "VANILLA"
    },
    {
      "packname": "festive-optifine",
      "url": "https://github.com/DBTDerpbox/LEB-Resources/blob/zip/zip/optifine/R26.4/festive.zip?raw\u003dtrue",
      "hash": "",
      "required": true,
      "hasPrompt": true,
      "message": "Legacy Edition Battle requires a resource pack to function properly!",
      "packCompatibility": "OPTIFINE"
    },
    {
      "packname": "fallout",
      "url": "https://github.com/DBTDerpbox/LEB-Resources/blob/zip/zip/standard/R26.4/fallout.zip?raw\u003dtrue",
      "hash": "",
      "required": true,
      "hasPrompt": true,
      "message": "Legacy Edition Battle requires a resource pack to function properly!",
      "packCompatibility": "VANILLA"
    },
    {
      "packname": "fallout-optifine",
      "url": "https://github.com/DBTDerpbox/LEB-Resources/blob/zip/zip/optifine/R26.4/fallout.zip?raw\u003dtrue",
      "hash": "",
      "required": true,
      "hasPrompt": true,
      "message": "Legacy Edition Battle requires a resource pack to function properly!",
      "packCompatibility": "OPTIFINE"
    },
    {
      "packname": "natural",
      "url": "https://github.com/DBTDerpbox/LEB-Resources/blob/zip/zip/standard/R26.4/natural.zip?raw\u003dtrue",
      "hash": "",
      "required": true,
      "hasPrompt": true,
      "message": "Legacy Edition Battle requires a resource pack to function properly!",
      "packCompatibility": "VANILLA"
    },
    {
      "packname": "natural-optifine",
      "url": "https://github.com/DBTDerpbox/LEB-Resources/blob/zip/zip/optifine/R26.4/natural.zip?raw\u003dtrue",
      "hash": "",
      "required": true,
      "hasPrompt": true,
      "message": "Legacy Edition Battle requires a resource pack to function properly!",
      "packCompatibility": "OPTIFINE"
    },
    {
      "packname": "cartoon",
      "url": "https://github.com/DBTDerpbox/LEB-Resources/blob/zip/zip/standard/R26.4/cartoon.zip?raw\u003dtrue",
      "hash": "",
      "required": true,
      "hasPrompt": true,
      "message": "Legacy Edition Battle requires a resource pack to function properly!",
      "packCompatibility": "VANILLA"
    },
    {
      "packname": "cartoon-optifine",
      "url": "https://github.com/DBTDerpbox/LEB-Resources/blob/zip/zip/optifine/R26.4/cartoon.zip?raw\u003dtrue",
      "hash": "",
      "required": true,
      "hasPrompt": true,
      "message": "Legacy Edition Battle requires a resource pack to function properly!",
      "packCompatibility": "OPTIFINE"
    }
  ]
}