{
  "pools": [
    {
      "rolls": 1,
      "entries": [
        {
          "type": "item",
          "weight": 1,
          "name": "minecraft:bow",
          "functions": [
            {
              "function": "set_count",
              "count": 1
            }
          ]
        }
      ]
    },
    {
      "rolls": 1,
      "entries": [
        {
          "type": "minecraft:item",
          "weight": 1,
          "name": "minecraft:tipped_arrow",
          "functions": [
            {
              "function": "minecraft:set_nbt",
              "tag": "{display:{Name:'{\"translate\":\"item.minecraft.tipped_arrow.effect.weakness\",\"italic\":false}',Lore:['[{\"translate\":\"effect.minecraft.weakness\",\"color\":\"red\",\"italic\":false},{\"text\":\" (0:07)\",\"italic\":false}]','{\"text\":\" \"}','{\"translate\":\"potion.whenDrank\",\"color\":\"dark_purple\",\"italic\":false}','[{\"text\":\"-4 \",\"color\":\"red\",\"italic\":false},{\"translate\":\"attribute.name.generic.attack_damage\",\"color\":\"red\",\"italic\":false}]']},HideFlags:32,custom_potion_effects:[{show_particles:1b,ambient:0b,id:\"minecraft:weakness\",amplifier:0b,duration:140,amplifier_int:0,show_icon:1b}],Potion:\"minecraft:water\"}"
            },
            {
              "function": "minecraft:set_count",
              "count": 5
            }
          ]
        }
      ]
    },
    {
      "rolls": 1,
      "entries": [
        {
          "type": "item",
          "weight": 1,
          "name": "minecraft:iron_boots",
          "functions": [
            {
              "function": "set_count",
              "count": 1
            },
            {
              "function": "set_nbt",
              "tag": "{display:{Lore:['[{\"text\":\"ยง9+2.0 \",\"color\":\"blue\",\"italic\":false},{\"translate\":\"attribute.name.generic.armor\"}]']},HideFlags:2,Enchantments:[{id:\"minecraft:depth_strider\",lvl:2s}]}"
            }
          ]
        }
      ]
    }
  ]
}
